Workbook

Sheet MENU

Sheet DESPESAS
A1: DESPESAS
B5: DATA | C5: CATEGORIA | D5: DESCRIÇÃO | E5: VALOR | F5: OBSERVAÇÃO | G5: MÊS | H5: ANO
B6: 46125 | C6: Apartamento | D6: 46113 | E6: 880 | F6: Boleto | G6: =MONTH(Tabela1[[#This Row],[DATA]]) -> 4 | H6: =YEAR(Tabela1[[#This Row],[DATA]]) -> 2026
B7: 46126 | C7: Condominio | D7: Apartamento | E7: 380 | F7: Boleto | G7: =MONTH(Tabela1[[#This Row],[DATA]]) -> 4 | H7: =YEAR(Tabela1[[#This Row],[DATA]]) -> 2026
B8: 46127 | C8: Supermercado | D8: Besteiras | E8: 300 | F8: Cartão Debito | G8: =MONTH(Tabela1[[#This Row],[DATA]]) -> 4 | H8: =YEAR(Tabela1[[#This Row],[DATA]]) -> 2026
B9: 46128 | C9: Saúde | D9: Dermatologista | E9: 350 | F9: Cartão Crédito | G9: =MONTH(Tabela1[[#This Row],[DATA]]) -> 4 | H9: =YEAR(Tabela1[[#This Row],[DATA]]) -> 2026
B10: 46129 | C10: Lazer | D10: Cinema | E10: 200 | F10: Cartão Debito | G10: =MONTH(Tabela1[[#This Row],[DATA]]) -> 4 | H10: =YEAR(Tabela1[[#This Row],[DATA]]) -> 2026
B11: 46130 | C11: Streamings | D11: Geral | E11: 200 | F11: Cartão Crédito | G11: =MONTH(Tabela1[[#This Row],[DATA]]) -> 4 | H11: =YEAR(Tabela1[[#This Row],[DATA]]) -> 2026
B12: 46131 | C12: Lazer | D12: Viagem | E12: 1700 | G12: =MONTH(Tabela1[[#This Row],[DATA]]) -> 4 | H12: =YEAR(Tabela1[[#This Row],[DATA]]) -> 2026
B13: 46042 | C13: Streamings | E13: 40 | G13: =MONTH(Tabela1[[#This Row],[DATA]]) -> 1 | H13: =YEAR(Tabela1[[#This Row],[DATA]]) -> 2026
B14: 46102 | C14: Streamings | E14: 50 | G14: =MONTH(Tabela1[[#This Row],[DATA]]) -> 3 | H14: =YEAR(Tabela1[[#This Row],[DATA]]) -> 2026
B15: 46235 | C15: Saúde | E15: 800 | G15: =MONTH(Tabela1[[#This Row],[DATA]]) -> 8 | H15: =YEAR(Tabela1[[#This Row],[DATA]]) -> 2026
B16: 46135 | G16: =MONTH(Tabela1[[#This Row],[DATA]]) -> 4 | H16: =YEAR(Tabela1[[#This Row],[DATA]]) -> 2026
B17: 46136 | G17: =MONTH(Tabela1[[#This Row],[DATA]]) -> 4 | H17: =YEAR(Tabela1[[#This Row],[DATA]]) -> 2026
B18: 46137 | G18: =MONTH(Tabela1[[#This Row],[DATA]]) -> 4 | H18: =YEAR(Tabela1[[#This Row],[DATA]]) -> 2026
B19: 46138 | G19: =MONTH(Tabela1[[#This Row],[DATA]]) -> 4 | H19: =YEAR(Tabela1[[#This Row],[DATA]]) -> 2026
B20: 46139 | G20: =MONTH(Tabela1[[#This Row],[DATA]]) -> 4 | H20: =YEAR(Tabela1[[#This Row],[DATA]]) -> 2026
B21: 46140 | G21: =MONTH(Tabela1[[#This Row],[DATA]]) -> 4 | H21: =YEAR(Tabela1[[#This Row],[DATA]]) -> 2026
B22: 46141 | G22: =MONTH(Tabela1[[#This Row],[DATA]]) -> 4 | H22: =YEAR(Tabela1[[#This Row],[DATA]]) -> 2026
B23: 46142 | G23: =MONTH(Tabela1[[#This Row],[DATA]]) -> 4 | H23: =YEAR(Tabela1[[#This Row],[DATA]]) -> 2026

Sheet LISTAS
A1: LISTAS
B5: DESPESAS | D5: RECEITAS
B6: Apartamento | D6: Salário
B7: Condominio | D7: Bônus
B8: Supermercado | D8: Investimento
B9: Saúde | D9: Trabalho Extra
B10: Lazer
B11: Streamings

Sheet RECEITAS
A1: RECEITAS
B5: DATA | C5: CATEGORIA | D5: DESCRIÇÃO | E5: VALOR | F5: OBSERVAÇÃO | G5: MÊS | H5: ANO
B6: 46125 | C6: Trabalho Extra | E6: 200 | G6: =MONTH(Tabela13[[#This Row],[DATA]]) -> 4 | H6: =YEAR(Tabela13[[#This Row],[DATA]]) -> 2026
B7: 46126 | C7: Salário | E7: 998 | G7: =MONTH(Tabela13[[#This Row],[DATA]]) -> 4 | H7: =YEAR(Tabela13[[#This Row],[DATA]]) -> 2026
B8: 46127 | C8: Bônus | E8: 150 | G8: =MONTH(Tabela13[[#This Row],[DATA]]) -> 4 | H8: =YEAR(Tabela13[[#This Row],[DATA]]) -> 2026
B9: 46128 | C9: Investimento | E9: 500 | G9: =MONTH(Tabela13[[#This Row],[DATA]]) -> 4 | H9: =YEAR(Tabela13[[#This Row],[DATA]]) -> 2026
B10: 46129 | C10: Bônus | E10: 200 | G10: =MONTH(Tabela13[[#This Row],[DATA]]) -> 4 | H10: =YEAR(Tabela13[[#This Row],[DATA]]) -> 2026
B11: 46130 | C11: Trabalho Extra | E11: 1700 | G11: =MONTH(Tabela13[[#This Row],[DATA]]) -> 4 | H11: =YEAR(Tabela13[[#This Row],[DATA]]) -> 2026
B12: 46131 | C12: Bônus | E12: 2000 | G12: =MONTH(Tabela13[[#This Row],[DATA]]) -> 4 | H12: =YEAR(Tabela13[[#This Row],[DATA]]) -> 2026
B13: 46042 | C13: Investimento | E13: 300 | G13: =MONTH(Tabela13[[#This Row],[DATA]]) -> 1 | H13: =YEAR(Tabela13[[#This Row],[DATA]]) -> 2026
B14: 46074 | C14: Trabalho Extra | E14: 300 | G14: =MONTH(Tabela13[[#This Row],[DATA]]) -> 2 | H14: =YEAR(Tabela13[[#This Row],[DATA]]) -> 2026
B15: 46103 | C15: Salário | E15: 2000 | G15: =MONTH(Tabela13[[#This Row],[DATA]]) -> 3 | H15: =YEAR(Tabela13[[#This Row],[DATA]]) -> 2026
B16: 46235 | C16: Investimento | E16: 4000 | G16: =MONTH(Tabela13[[#This Row],[DATA]]) -> 8 | H16: =YEAR(Tabela13[[#This Row],[DATA]]) -> 2026

Sheet DASHBOARD
A1: DASHBOARD
C6: ANO
C7: 2026 | D7: selecionar ano
C9: MESES | D9: ENTRADAS | E9: SAIDAS | F9: ACUMULADO | G9: SALDO | I9: DESPESAS | J9: TOTAL | L9: RECEITAS | M9: TOTAL
C10: 1 | D10: =SUMIFS(RECEITAS!E:E,RECEITAS!G:G,DASHBOARD!C10,RECEITAS!H:H,DASHBOARD!$C$7) -> 300 | E10: =SUMIFS(DESPESAS!E:E,DESPESAS!G:G,DASHBOARD!C10,DESPESAS!H:H,DASHBOARD!$C$7) -> 40 | F10: =G10 -> 260 | G10: =D10-E10 -> 260 | I10: =LISTAS!B6 -> Apartamento | J10: =SUMIFS(DESPESAS!E:E,DESPESAS!C:C,DASHBOARD!I10,DESPESAS!H:H,DASHBOARD!$C$7) -> 880 | L10: =LISTAS!D6 -> Salário | M10: =SUMIFS(RECEITAS!E:E,RECEITAS!C:C,DASHBOARD!L10,RECEITAS!H:H,DASHBOARD!$C$7) -> 2998
C11: 2 | D11: =SUMIFS(RECEITAS!E:E,RECEITAS!G:G,DASHBOARD!C11,RECEITAS!H:H,DASHBOARD!$C$7) -> 300 | E11: =SUMIFS(DESPESAS!E:E,DESPESAS!G:G,DASHBOARD!C11,DESPESAS!H:H,DASHBOARD!$C$7) -> 0 | F11: =F10+G11 -> 560 | G11: =D11-E11 -> 300 | I11: =LISTAS!B7 -> Condominio | J11: =SUMIFS(DESPESAS!E:E,DESPESAS!C:C,DASHBOARD!I11,DESPESAS!H:H,DASHBOARD!$C$7) -> 380 | L11: =LISTAS!D7 -> Bônus | M11: =SUMIFS(RECEITAS!E:E,RECEITAS!C:C,DASHBOARD!L11,RECEITAS!H:H,DASHBOARD!$C$7) -> 2350
C12: 3 | D12: =SUMIFS(RECEITAS!E:E,RECEITAS!G:G,DASHBOARD!C12,RECEITAS!H:H,DASHBOARD!$C$7) -> 2000 | E12: =SUMIFS(DESPESAS!E:E,DESPESAS!G:G,DASHBOARD!C12,DESPESAS!H:H,DASHBOARD!$C$7) -> 50 | F12: =F11+G12 -> 2510 | G12: =D12-E12 -> 1950 | I12: =LISTAS!B8 -> Supermercado | J12: =SUMIFS(DESPESAS!E:E,DESPESAS!C:C,DASHBOARD!I12,DESPESAS!H:H,DASHBOARD!$C$7) -> 300 | L12: =LISTAS!D8 -> Investimento | M12: =SUMIFS(RECEITAS!E:E,RECEITAS!C:C,DASHBOARD!L12,RECEITAS!H:H,DASHBOARD!$C$7) -> 4800
C13: 4 | D13: =SUMIFS(RECEITAS!E:E,RECEITAS!G:G,DASHBOARD!C13,RECEITAS!H:H,DASHBOARD!$C$7) -> 5748 | E13: =SUMIFS(DESPESAS!E:E,DESPESAS!G:G,DASHBOARD!C13,DESPESAS!H:H,DASHBOARD!$C$7) -> 4010 | F13: =F12+G13 -> 4248 | G13: =D13-E13 -> 1738 | I13: =LISTAS!B9 -> Saúde | J13: =SUMIFS(DESPESAS!E:E,DESPESAS!C:C,DASHBOARD!I13,DESPESAS!H:H,DASHBOARD!$C$7) -> 1150 | L13: =LISTAS!D9 -> Trabalho Extra | M13: =SUMIFS(RECEITAS!E:E,RECEITAS!C:C,DASHBOARD!L13,RECEITAS!H:H,DASHBOARD!$C$7) -> 2200
C14: 5 | D14: =SUMIFS(RECEITAS!E:E,RECEITAS!G:G,DASHBOARD!C14,RECEITAS!H:H,DASHBOARD!$C$7) -> 0 | E14: =SUMIFS(DESPESAS!E:E,DESPESAS!G:G,DASHBOARD!C14,DESPESAS!H:H,DASHBOARD!$C$7) -> 0 | F14: =F13+G14 -> 4248 | G14: =D14-E14 -> 0 | I14: =LISTAS!B10 -> Lazer | J14: =SUMIFS(DESPESAS!E:E,DESPESAS!C:C,DASHBOARD!I14,DESPESAS!H:H,DASHBOARD!$C$7) -> 1900 | L14: =LISTAS!D10 -> 0 | M14: =SUMIFS(RECEITAS!E:E,RECEITAS!C:C,DASHBOARD!L14,RECEITAS!H:H,DASHBOARD!$C$7) -> 0
C15: 6 | D15: =SUMIFS(RECEITAS!E:E,RECEITAS!G:G,DASHBOARD!C15,RECEITAS!H:H,DASHBOARD!$C$7) -> 0 | E15: =SUMIFS(DESPESAS!E:E,DESPESAS!G:G,DASHBOARD!C15,DESPESAS!H:H,DASHBOARD!$C$7) -> 0 | F15: =F14+G15 -> 4248 | G15: =D15-E15 -> 0 | I15: =LISTAS!B11 -> Streamings | J15: =SUMIFS(DESPESAS!E:E,DESPESAS!C:C,DASHBOARD!I15,DESPESAS!H:H,DASHBOARD!$C$7) -> 290 | L15: =LISTAS!D11 -> 0 | M15: =SUMIFS(RECEITAS!E:E,RECEITAS!C:C,DASHBOARD!L15,RECEITAS!H:H,DASHBOARD!$C$7) -> 0
C16: 7 | D16: =SUMIFS(RECEITAS!E:E,RECEITAS!G:G,DASHBOARD!C16,RECEITAS!H:H,DASHBOARD!$C$7) -> 0 | E16: =SUMIFS(DESPESAS!E:E,DESPESAS!G:G,DASHBOARD!C16,DESPESAS!H:H,DASHBOARD!$C$7) -> 0 | F16: =F15+G16 -> 4248 | G16: =D16-E16 -> 0 | I16: =LISTAS!B12 -> 0 | J16: =SUMIFS(DESPESAS!E:E,DESPESAS!C:C,DASHBOARD!I16,DESPESAS!H:H,DASHBOARD!$C$7) -> 0 | L16: =LISTAS!D12 -> 0 | M16: =SUMIFS(RECEITAS!E:E,RECEITAS!C:C,DASHBOARD!L16,RECEITAS!H:H,DASHBOARD!$C$7) -> 0
C17: 8 | D17: =SUMIFS(RECEITAS!E:E,RECEITAS!G:G,DASHBOARD!C17,RECEITAS!H:H,DASHBOARD!$C$7) -> 4000 | E17: =SUMIFS(DESPESAS!E:E,DESPESAS!G:G,DASHBOARD!C17,DESPESAS!H:H,DASHBOARD!$C$7) -> 800 | F17: =F16+G17 -> 7448 | G17: =D17-E17 -> 3200 | I17: =LISTAS!B13 -> 0 | J17: =SUMIFS(DESPESAS!E:E,DESPESAS!C:C,DASHBOARD!I17,DESPESAS!H:H,DASHBOARD!$C$7) -> 0 | L17: =LISTAS!D13 -> 0 | M17: =SUMIFS(RECEITAS!E:E,RECEITAS!C:C,DASHBOARD!L17,RECEITAS!H:H,DASHBOARD!$C$7) -> 0
C18: 9 | D18: =SUMIFS(RECEITAS!E:E,RECEITAS!G:G,DASHBOARD!C18,RECEITAS!H:H,DASHBOARD!$C$7) -> 0 | E18: =SUMIFS(DESPESAS!E:E,DESPESAS!G:G,DASHBOARD!C18,DESPESAS!H:H,DASHBOARD!$C$7) -> 0 | F18: =F17+G18 -> 7448 | G18: =D18-E18 -> 0 | I18: =LISTAS!B14 -> 0 | J18: =SUMIFS(DESPESAS!E:E,DESPESAS!C:C,DASHBOARD!I18,DESPESAS!H:H,DASHBOARD!$C$7) -> 0 | L18: =LISTAS!D14 -> 0 | M18: =SUMIFS(RECEITAS!E:E,RECEITAS!C:C,DASHBOARD!L18,RECEITAS!H:H,DASHBOARD!$C$7) -> 0
C19: 10 | D19: =SUMIFS(RECEITAS!E:E,RECEITAS!G:G,DASHBOARD!C19,RECEITAS!H:H,DASHBOARD!$C$7) -> 0 | E19: =SUMIFS(DESPESAS!E:E,DESPESAS!G:G,DASHBOARD!C19,DESPESAS!H:H,DASHBOARD!$C$7) -> 0 | F19: =F18+G19 -> 7448 | G19: =D19-E19 -> 0 | I19: =LISTAS!B15 -> 0 | J19: =SUMIFS(DESPESAS!E:E,DESPESAS!C:C,DASHBOARD!I19,DESPESAS!H:H,DASHBOARD!$C$7) -> 0 | L19: =LISTAS!D15 -> 0 | M19: =SUMIFS(RECEITAS!E:E,RECEITAS!C:C,DASHBOARD!L19,RECEITAS!H:H,DASHBOARD!$C$7) -> 0
C20: 11 | D20: =SUMIFS(RECEITAS!E:E,RECEITAS!G:G,DASHBOARD!C20,RECEITAS!H:H,DASHBOARD!$C$7) -> 0 | E20: =SUMIFS(DESPESAS!E:E,DESPESAS!G:G,DASHBOARD!C20,DESPESAS!H:H,DASHBOARD!$C$7) -> 0 | F20: =F19+G20 -> 7448 | G20: =D20-E20 -> 0 | I20: =LISTAS!B16 -> 0 | J20: =SUMIFS(DESPESAS!E:E,DESPESAS!C:C,DASHBOARD!I20,DESPESAS!H:H,DASHBOARD!$C$7) -> 0 | L20: =LISTAS!D16 -> 0 | M20: =SUMIFS(RECEITAS!E:E,RECEITAS!C:C,DASHBOARD!L20,RECEITAS!H:H,DASHBOARD!$C$7) -> 0
C21: 12 | D21: =SUMIFS(RECEITAS!E:E,RECEITAS!G:G,DASHBOARD!C21,RECEITAS!H:H,DASHBOARD!$C$7) -> 0 | E21: =SUMIFS(DESPESAS!E:E,DESPESAS!G:G,DASHBOARD!C21,DESPESAS!H:H,DASHBOARD!$C$7) -> 0 | F21: =F20+G21 -> 7448 | G21: =D21-E21 -> 0 | I21: =LISTAS!B17 -> 0 | J21: =SUMIFS(DESPESAS!E:E,DESPESAS!C:C,DASHBOARD!I21,DESPESAS!H:H,DASHBOARD!$C$7) -> 0 | L21: =LISTAS!D17 -> 0 | M21: =SUMIFS(RECEITAS!E:E,RECEITAS!C:C,DASHBOARD!L21,RECEITAS!H:H,DASHBOARD!$C$7) -> 0
C22: TOTAL | D22: =SUM(D10:D21) -> 12348 | E22: =SUM(E10:E21) -> 4900 | F22: =F21 -> 7448 | G22: =SUM(G10:G21) -> 7448 | I22: =LISTAS!B18 -> 0 | J22: =SUMIFS(DESPESAS!E:E,DESPESAS!C:C,DASHBOARD!I22,DESPESAS!H:H,DASHBOARD!$C$7) -> 0 | L22: =LISTAS!D18 -> 0 | M22: =SUMIFS(RECEITAS!E:E,RECEITAS!C:C,DASHBOARD!L22,RECEITAS!H:H,DASHBOARD!$C$7) -> 0

Sheet Plan1
J23: PARA VOCÊ MEU BEM
